{
  "company": [
    {
      "title": "双益农业新生产线正式投产",
      "date": "2026-05-20",
      "url": "#"
    },
    {
      "title": "公司参加农产品加工行业交流会",
      "date": "2026-04-15",
      "url": "#"
    },
    {
      "title": "双益农业荣获\"诚信企业\"称号",
      "date": "2026-03-28",
      "url": "#"
    }
  ],
  "industry": [
    {
      "title": "马铃薯淀粉行业市场分析报告",
      "date": "2026-05-18",
      "url": "#"
    },
    {
      "title": "淀粉加工技术发展趋势",
      "date": "2026-04-10",
      "url": "#"
    },
    {
      "title": "国家政策支持农业产业化发展",
      "date": "2026-03-22",
      "url": "#"
    }
  ],
  "knowledge": [
    {
      "title": "马铃薯的营养价值与功效",
      "date": "2026-05-12",
      "url": "#"
    },
    {
      "title": "如何挑选优质马铃薯",
      "date": "2026-04-05",
      "url": "#"
    },
    {
      "title": "马铃薯种植技术要点",
      "date": "2026-03-18",
      "url": "#"
    }
  ]
}
